agogos/__init__.py
agogos/_core.py
agogos/training.py
agogos/transforming.py
agogos-0.3.4.dist-info/LICENSE
agogos-0.3.4.dist-info/METADATA
agogos-0.3.4.dist-info/WHEEL
agogos-0.3.4.dist-info/top_level.txt
agogos-0.3.4.dist-info/RECORD
