Metadata-Version: 2.1
Name: agogos
Version: 0.3.4
Summary: Package that creates the underlying construction of a machine learning pipeline
Author-email: Jasper van Selm <jmvanselm@gmail.com>
Classifier: Programming Language :: Python :: 3
Classifier: License :: OSI Approved :: MIT License
Classifier: Operating System :: OS Independent
Requires-Python: >=3.10
License-File: LICENSE
Requires-Dist: joblib >=1.3.2
